currencies_lib/__init__.py
currencies_lib/currencies.py
currencies_lib-1.0.3.dist-info/LICENSE
currencies_lib-1.0.3.dist-info/METADATA
currencies_lib-1.0.3.dist-info/WHEEL
currencies_lib-1.0.3.dist-info/top_level.txt
currencies_lib-1.0.3.dist-info/RECORD
