Metadata-Version: 2.1
Name: currencies_lib
Version: 1.0.3
Summary: A currency formatter for many currencies
Home-page: https://github.com/iamtwobe/currencies_lib
Author: iamtwobe
Author-email: contato.iamtwobe@gmail.com
License: MIT
Classifier: License :: OSI Approved :: MIT License
Classifier: Programming Language :: Python :: 3
Classifier: Operating System :: OS Independent
Requires-Python: >=3.10
License-File: LICENSE
